deep_oc_client/__init__.py
deep_oc_client/exceptions.py
deep_oc_client/shell.py
deep_oc_client/version.py
deep_oc_client/client/__init__.py
deep_oc_client/client/client.py
deep_oc_client/client/modules.py
deep_oc_client/cmd/__init__.py
deep_oc_client/cmd/modules.py
deep_oc_client/tests/__init__.py
deep_oc_client/tests/base.py
deep_oc_client/tests/test_deep_oc_client.py
deep_oc_client-0.1.0.dist-info/AUTHORS
deep_oc_client-0.1.0.dist-info/LICENSE
deep_oc_client-0.1.0.dist-info/METADATA
deep_oc_client-0.1.0.dist-info/WHEEL
deep_oc_client-0.1.0.dist-info/entry_points.txt
deep_oc_client-0.1.0.dist-info/pbr.json
deep_oc_client-0.1.0.dist-info/top_level.txt
deep_oc_client-0.1.0.dist-info/RECORD
