Metadata-Version: 2.1
Name: deep-oc-client
Version: 0.1.0
Summary: DEEP OC Command Line Interface (DEEP OC CLI)
Home-page: https://marketplace.deep-hybrid-datacloud.eu/
Author: Alvaro Lopez Garcia
Author-email: aloga@ifca.unican.es
License: UNKNOWN
Platform: UNKNOWN
Classifier: Development Status :: 5 - Production/Stable
Classifier: Environment :: Console
Classifier: Environment :: Web Environment
Classifier: Framework :: Flask
Classifier: Intended Audience :: Developers
Classifier: Intended Audience :: Information Technology
Classifier: Intended Audience :: Science/Research
Classifier: Intended Audience :: System Administrators
Classifier: License :: OSI Approved :: Apache Software License
Classifier: Operating System :: OS Independent
Classifier: Programming Language :: Python
Classifier: Programming Language :: Python :: 3
Classifier: Topic :: Internet :: WWW/HTTP
Classifier: Topic :: Scientific/Engineering :: Artificial Intelligence
Classifier: Topic :: Scientific/Engineering :: Image Recognition
Classifier: Topic :: Scientific/Engineering :: Information Analysis
Requires-Dist: pbr (!=2.1.0,>=2.0.0)
Requires-Dist: six (>=1.10.0)
Requires-Dist: setuptools (!=24.0.0,!=34.0.0,!=34.0.1,!=34.0.2,!=34.0.3,!=34.1.0,!=34.1.1,!=34.2.0,!=34.3.0,!=34.3.1,!=34.3.2,!=36.2.0,>=21.0.0)
Requires-Dist: docutils (>=0.14.0)
Requires-Dist: cliff (!=2.9.0,>=2.8.0)
Requires-Dist: requests
